iara_stt_training/GRAPH_VERSION
iara_stt_training/VERSION
iara_stt_training/__init__.py
iara_stt_training/deepspeech_model.py
iara_stt_training/evaluate.py
iara_stt_training/evaluate_export.py
iara_stt_training/evaluate_flashlight.py
iara_stt_training/evaluate_from_csv.py
iara_stt_training/evaluate_wav2vec2am.py
iara_stt_training/export.py
iara_stt_training/train.py
iara_stt_training/training_graph_inference.py
iara_stt_training/training_graph_inference_flashlight.py
iara_stt_training/transcribe.py
iara_stt_training/util/__init__.py
iara_stt_training/util/audio.py
iara_stt_training/util/augmentations.py
iara_stt_training/util/auto_input.py
iara_stt_training/util/check_characters.py
iara_stt_training/util/checkpoints.py
iara_stt_training/util/config.py
iara_stt_training/util/downloader.py
iara_stt_training/util/evaluate_tools.py
iara_stt_training/util/feeding.py
iara_stt_training/util/gpu.py
iara_stt_training/util/helpers.py
iara_stt_training/util/importers.py
iara_stt_training/util/io.py
iara_stt_training/util/lm_optimize.py
iara_stt_training/util/lm_optimize_wav2vec2am.py
iara_stt_training/util/multiprocessing.py
iara_stt_training/util/sample_collections.py
iara_stt_training/util/stm.py
iara_stt_training/util/text.py
iara_stt_training-1.6.2.dist-info/LICENSE
iara_stt_training-1.6.2.dist-info/METADATA
iara_stt_training-1.6.2.dist-info/WHEEL
iara_stt_training-1.6.2.dist-info/top_level.txt
iara_stt_training-1.6.2.dist-info/RECORD
