Metadata-Version: 2.1
Name: iara_stt_training
Version: 1.6.2
Summary: Training code for Coqui STT
Home-page: https://github.com/coqui-ai/STT
Author: Coqui STT authors
License: MPL-2.0
Classifier: Development Status :: 3 - Alpha
Classifier: Intended Audience :: Developers
Classifier: Topic :: Multimedia :: Sound/Audio :: Speech
Classifier: License :: OSI Approved :: Mozilla Public License 2.0 (MPL 2.0)
Classifier: Programming Language :: Python :: 3
Requires-Python: >=3.7, <3.10
License-File: LICENSE
Requires-Dist: attrdict
Requires-Dist: attrs <22
Requires-Dist: bs4
Requires-Dist: coqpit
Requires-Dist: numpy <1.19.0
Requires-Dist: optuna
Requires-Dist: numba <=0.53.1
Requires-Dist: opuslib ==2.0.0
Requires-Dist: pandas
Requires-Dist: progressbar2
Requires-Dist: protobuf <=3.20.1
Requires-Dist: pyogg >=0.6.14a1
Requires-Dist: resampy >=0.4.0
Requires-Dist: requests
Requires-Dist: semver
Requires-Dist: six
Requires-Dist: sox
Requires-Dist: soundfile
Requires-Dist: tqdm
Requires-Dist: webdataset ==0.1.103
Requires-Dist: miniaudio
Requires-Dist: clearml
Requires-Dist: iara-stt-ctcdecoder ==1.6.2
Requires-Dist: tensorflow ==1.15.4
Provides-Extra: onnxruntime
Requires-Dist: onnxruntime ==1.11.0 ; extra == 'onnxruntime'
Provides-Extra: transcribe
Requires-Dist: webrtcvad ==2.0.10 ; extra == 'transcribe'
